tapd
