Metadata-Version: 1.0
Name: tapd
Version: 2.0.0
Summary: TAPD service driver
Home-page: https://gitlab.pin-dao.cn/TM-QA
Author: chendb
Author-email: love_vida@163.com
License: Apache License 2.0
Platform: any
